<table-wrap xmlns:xlink="http://www.w3.org/1999/xlink" id="tblu7" position="anchor"><table frame="hsides" rules="groups"><thead><tr><th>Reagent</th><th>Type</th><th>Manufacturer</th><th>Catalog #</th><th>Comments</th></tr></thead><tbody><tr><td>pMIR-CD443&#8242; UTR</td><td>Plasmid</td><td colspan="2">Provided by the original author</td><td>Vector containing the 3&#8242; UTR of CD44 fused to luciferase</td></tr><tr><td>pMIR-CD44M1M23&#8242; UTR</td><td>Plasmid</td><td colspan="2">Provided by the original author</td><td>Vector containing the 3&#8242; UTR of CD44 fused to luciferase, with both seed regions mutated</td></tr><tr><td>phRL-CMV</td><td>Plasmid</td><td colspan="2">Provided by the original author</td><td>Renilla control</td></tr><tr><td>DU145 cells</td><td>Cells</td><td>ATCC</td><td>HTB-81</td><td>&#8211;</td></tr><tr><td>Dual luciferase assay</td><td>Kit</td><td>Promega</td><td>E1960</td><td>&#8211;</td></tr><tr><td>miR34-a oligo</td><td>Oligo</td><td colspan="2">Synthesis left to the discretion of the replicating lab</td><td>&#8211;</td></tr><tr><td>Non-coding control oligo</td><td>Oligo</td><td colspan="2">Synthesis left to the discretion of the replicating lab</td><td>&#8211;</td></tr><tr><td>RPMI 1640</td><td>Media</td><td>Thermal Scientific</td><td>SH30809</td><td>&#8211;</td></tr><tr><td>Fetal bovine serum (FBS)</td><td>Reagent</td><td>Gibco</td><td>10099-133</td><td>&#8211;</td></tr><tr><td>Lipofectamine 2000</td><td>Reagent</td><td>Life Technologies</td><td>11668027</td><td>&#8211;</td></tr><tr><td>Fluorescence plate reader</td><td>Equipment</td><td>PerkinElmer</td><td>Envision 2104 multilabel reader</td><td>Replaces Gen-Probe Leader 50i lunimometer used originally</td></tr><tr><td>Endo-free maxiprep kit</td><td>Kit</td><td>Qiagen</td><td>12362</td><td>Original unspecified</td></tr><tr><td>miR-34a mirVana mRNA mimic</td><td>Oligo</td><td>Ambion/Life Technologies</td><td>4464066</td><td>Termed the miR34a oligo</td></tr><tr><td>mirVana miRNA mimic, miR-1 positive control</td><td>Oligo</td><td>Ambion/Life Technologies</td><td>464062</td><td>Termed the NC oligo</td></tr></tbody></table></table-wrap>