<table-wrap xmlns:ali="http://www.niso.org/schemas/ali/1.0/" xmlns:xlink="http://www.w3.org/1999/xlink" id="table4" position="float"><label>Table 4.</label><caption><title>Uniquely mapped RNA identified via phrap adjacent AAGAG(&gt;10) containing blocks</title></caption><table frame="hsides" rules="groups"><thead><tr><th valign="bottom">Chr</th><th valign="bottom">e0-2hr</th><th valign="bottom">e2-4hr</th><th valign="bottom">e4-8hr</th><th valign="bottom">e8-12hr</th><th valign="bottom">e12-14hr</th><th valign="bottom">e14-16hr</th><th valign="bottom">e16-20hr</th><th valign="bottom">e20-24hr</th></tr></thead><tbody><tr><td>2R</td><td>NA</td><td>NA</td><td>NA</td><td>NA</td><td>NA</td><td>NA</td><td>chr2R.1825640.1825699</td><td>NA</td></tr><tr><td>X</td><td>NA</td><td>NA</td><td>NA</td><td>NA</td><td>NA</td><td>NA</td><td>NA</td><td>chrX.12660077.12660134</td></tr><tr><td>X</td><td>NA</td><td>NA</td><td>NA</td><td>NA</td><td>NA</td><td>NA</td><td>chrX.11830795.11830858</td><td>NA</td></tr><tr><td>X</td><td>chrX.22453019.22453120</td><td>NA</td><td>chrX.22453019.22453182</td><td>NA</td><td>chrX.22453019.22453163</td><td>chrX.22453019.22453177</td><td>chrX.22453019.22453093</td><td>chrX. <break/>22453019.22453196</td></tr></tbody></table></table-wrap>