<table-wrap xmlns:ali="http://www.niso.org/schemas/ali/1.0/" xmlns:xlink="http://www.w3.org/1999/xlink" id="table1" position="float"><object-id pub-id-type="doi">10.7554/eLife.40179.009</object-id><label>Table 1.</label><caption><title>Contribution of <italic>Mef2c-AHF</italic>, <italic>Islet1</italic>, <italic>Mesp1</italic> and <italic>Pax3</italic> lineages to neck and pectoral musculature.</title></caption><table frame="hsides" rules="groups"><thead><tr><th><italic>Mef2c/Islet1/Mesp1-</italic>derived muscles</th><th><italic>Mesp1/Pax3-</italic>derived muscles</th><th><italic>Pax3</italic>- derived muscles</th></tr></thead><tbody><tr><td>Mylohyoid <break/>Digastric muscles&#160; <break/> <break/> <break/>Pharyngeal muscles <break/>Intrinsic laryngeal muscles <break/>Esophagus striated muscle&#160; <break/> <break/>Sternocleidomastoid&#160; <break/>Acromiotrapezius&#160; <break/>Spinotrapezius&#160; <break/></td><td>Epaxial neck muscles <break/>(splenius, semispinalis, <break/>levator scapula, <break/>rhomboid occipitalis, <break/>suboccipital and <break/>postvertebral muscles) <break/> <break/>Hypaxial neck muscles <break/>(tongue muscles*, <break/>infrahyoid muscles, <break/>longus capitis, longus colli)</td><td>Scapular muscles <break/>(supraspinatus, Infraspinatus, <break/>subscapularis) <break/> <break/>Pectoralis <break/> <break/>Latissimus dorsi<sup>&#8224;</sup> <break/>Cutaneous maximus<sup>&#8224;</sup></td></tr><tr><td><bold>Branchiomeric myogenic program</bold></td><td><bold>Anterior-most somite myogenic program</bold></td><td><bold>More posterior somite myogenic program</bold></td></tr></tbody></table><table-wrap-foot><fn><p>*Including intrinsic and extrinsic tongue muscles of somitic origin</p><p><sup>&#8224;</sup>Also derived from an <italic>Islet1</italic> lineage</p></fn></table-wrap-foot></table-wrap>