<table-wrap xmlns:mml="http://www.w3.org/1998/Math/MathML" xmlns:xlink="http://www.w3.org/1999/xlink" id="tbl2" position="float"><object-id pub-id-type="doi">10.7554/eLife.09066.005</object-id><label>Table 2.</label><caption><p>Mo coordination geometry in the active site of SorT.</p><p><bold>DOI:</bold> <ext-link ext-link-type="doi" xlink:href="10.7554/eLife.09066.005">http://dx.doi.org/10.7554/eLife.09066.005</ext-link></p></caption><table frame="hsides" rules="groups"><thead><tr><th>Bond</th><th>Distance (&#197;)</th></tr></thead><tbody><tr><td>Mo-S1 (pterin)</td><td>2.4</td></tr><tr><td>Mo-S2 (pterin)</td><td>2.4</td></tr><tr><td>Mo-S (Cys 127)</td><td>2.3</td></tr><tr><td>Mo=O</td><td>1.7</td></tr><tr><td>Mo-OH/H<sub>2</sub>O</td><td>1.9</td></tr></tbody></table></table-wrap>