<table-wrap xmlns:mml="http://www.w3.org/1998/Math/MathML" xmlns:xlink="http://www.w3.org/1999/xlink" id="tbl3" position="float"><object-id pub-id-type="doi">10.7554/eLife.18566.035</object-id><label>Table 3.</label><caption><p>Electrophysiological characteristics of each model cell type. For more information about model electrophysiology, see the Appendix.</p><p><bold>DOI:</bold> <ext-link ext-link-type="doi" xlink:href="10.7554/eLife.18566.035">http://dx.doi.org/10.7554/eLife.18566.035</ext-link></p></caption><table frame="hsides" rules="groups"><thead><tr><th align="center">Condition</th><th align="center">Pyr</th><th align="center">PV+B</th><th align="center">CCK+B</th><th align="center">SC-A</th><th align="center">Axo</th><th align="center">Bis</th><th align="center">O-LM</th><th align="center">Ivy</th><th align="center">NGF</th></tr></thead><tbody><tr><td align="left">Resting Membrane Potential (mV)</td><td align="right">&#8722;63.0</td><td align="right">&#8722;65.0</td><td align="right">&#8722;70.6</td><td align="right">&#8722;70.5</td><td align="right">&#8722;65.0</td><td align="right">&#8722;67.0</td><td align="right">&#8722;71.5</td><td align="right">&#8722;60.0</td><td align="right">&#8722;60.0</td></tr><tr><td align="left">Input Resistance (M<inline-formula><mml:math id="inf13"><mml:mi mathvariant="normal">&#937;</mml:mi></mml:math></inline-formula>)</td><td align="right">62.2</td><td align="right">52.0</td><td align="right">211.0</td><td align="right">272.4</td><td align="right">52.0</td><td align="right">98.7</td><td align="right">343.8</td><td align="right">100.0</td><td align="right">100.0</td></tr><tr><td align="left">Membrane Tau (ms)</td><td align="right">4.8</td><td align="right">6.9</td><td align="right">22.6</td><td align="right">24.4</td><td align="right">7.0</td><td align="right">14.7</td><td align="right">22.4</td><td align="right">21.1</td><td align="right">21.1</td></tr><tr><td align="left">Rheobase (pA)</td><td align="right">250.0</td><td align="right">300.0</td><td align="right">60.0</td><td align="right">40.0</td><td align="right">200.0</td><td align="right">350.0</td><td align="right">50.0</td><td align="right">160.0</td><td align="right">170.0</td></tr><tr><td align="left">Threshold (mV)</td><td align="right">52.0</td><td align="right">&#8722;36.6</td><td align="right">&#8722;40.6</td><td align="right">&#8722;43.1</td><td align="right">&#8722;41.6</td><td align="right">&#8722;28.1</td><td align="right">100.2</td><td align="right">&#8722;27.6</td><td align="right">&#8722;27.7</td></tr><tr><td align="left">Delay to 1st Spike (ms)</td><td align="right">12.4</td><td align="right">74.6</td><td align="right">166.6</td><td align="right">127.7</td><td align="right">43.5</td><td align="right">28.4</td><td align="right">8.9</td><td align="right">173.3</td><td align="right">119.0</td></tr><tr><td align="left">Half-Width (ms)</td><td align="right">80.7</td><td align="right">0.9</td><td align="right">1.9</td><td align="right">1.6</td><td align="right">0.6</td><td align="right">0.5</td><td align="right">112.9</td><td align="right">0.6</td><td align="right">0.6</td></tr></tbody></table></table-wrap>