<table-wrap xmlns:ali="http://www.niso.org/schemas/ali/1.0/" xmlns:mml="http://www.w3.org/1998/Math/MathML" xmlns:xlink="http://www.w3.org/1999/xlink" id="table2" position="float"><label>Table 2.</label><caption><title>Estimated parameters of the second order input-output model for each fish as well as the merged fish.</title></caption><table frame="hsides" rules="groups"><thead><tr><th/><th><italic>Fish 1</italic></th><th><italic>Fish 2</italic></th><th><italic>Fish 3</italic></th><th><italic>Merged</italic></th></tr></thead><tbody><tr><td><inline-formula><mml:math id="inf60"><mml:mi>A</mml:mi></mml:math></inline-formula></td><td>0.53</td><td>0.60</td><td>0.52</td><td>0.57</td></tr><tr><td><inline-formula><mml:math id="inf61"><mml:mi>&#958;</mml:mi></mml:math></inline-formula></td><td>0.58</td><td>0.55</td><td>0.52</td><td>0.55</td></tr><tr><td><inline-formula><mml:math id="inf62"><mml:mrow><mml:mpadded width="+1.7pt"><mml:msub><mml:mi>&#969;</mml:mi><mml:mi>n</mml:mi></mml:msub></mml:mpadded><mml:mo>&#8290;</mml:mo><mml:mrow><mml:mo stretchy="false">(</mml:mo><mml:mrow><mml:mrow><mml:mi>r</mml:mi><mml:mo>&#8290;</mml:mo><mml:mi>a</mml:mi><mml:mo>&#8290;</mml:mo><mml:mi>d</mml:mi></mml:mrow><mml:mo>/</mml:mo><mml:mi>s</mml:mi></mml:mrow><mml:mo stretchy="false">)</mml:mo></mml:mrow></mml:mrow></mml:math></inline-formula></td><td>8.55</td><td>9.51</td><td>7.88</td><td>8.50</td></tr></tbody></table></table-wrap>