<table-wrap xmlns:mml="http://www.w3.org/1998/Math/MathML" xmlns:xlink="http://www.w3.org/1999/xlink" id="tbl2" position="float"><object-id pub-id-type="doi">10.7554/eLife.20914.021</object-id><label>Table 2.</label><caption><p>Dietary regimes used to maintain B6C3F1 mice.</p><p><bold>DOI:</bold> <ext-link ext-link-type="doi" xlink:href="10.7554/eLife.20914.021">http://dx.doi.org/10.7554/eLife.20914.021</ext-link></p></caption><table frame="hsides" rules="groups"><thead><tr><th><p>Experimental group</p></th><th><p>Chow 5 K54</p> </th><th><p>Drinking water (ad libitum)</p></th><th><p>Number of mice</p></th></tr></thead><tbody><tr><td><p>Control</p></td><td><p>ad libitum</p></td><td><p>Regular water<sup>*</sup></p> </td><td><p>335</p></td></tr><tr><td><p>Dietary restriction</p></td><td><p>60% of ad libitum</p></td><td><p>Regular water</p></td><td><p>60</p></td></tr><tr><td><p>Magnesium acetate supplemented</p></td><td><p>ad libitum</p></td><td><p>1 g/l Mg(CH<sub>3</sub>COO)<sub>2</sub>.(H<sub>2</sub>O)<sub>4</sub> in regular water</p></td><td><p>15</p></td></tr><tr><td><p>Magnesium chloride supplemented</p></td><td><p>ad libitum</p></td><td><p>1 g/l MgCl<sub>2</sub> in regular water</p></td><td><p>15</p></td></tr><tr><td><p>Magnesium hydroxide supplemented</p></td><td><p>ad libitum</p></td><td><p>14 mg/l Mg(OH)<sub>2</sub> in regular water<sup>&#8224;</sup></p> </td><td><p>15</p></td></tr><tr><td><p>Calcium chloride supplemented</p></td><td><p>ad libitum</p></td><td><p>0.8 g/l CaCl<sub>2</sub> in regular water</p></td><td><p>15</p></td></tr></tbody></table><table-wrap-foot><fn id="tblfn3"><p><sup>*</sup>Regular water contained 0.44 mg/l Mg<sup>2+</sup>.</p></fn><fn id="tblfn4"><p><sup>&#8224;</sup>Mg(OH)<sub>2</sub> concentration was lowered to prevent overall alkalization of the diet.</p></fn></table-wrap-foot></table-wrap>