<table-wrap xmlns:xlink="http://www.w3.org/1999/xlink" id="tbl1" position="float"><object-id pub-id-type="doi">10.7554/eLife.06057.019</object-id><label>Table 1.</label><caption><p><italic>De novo</italic> mutation profiles for human NIPBL and Mau2</p><p><bold>DOI:</bold> <ext-link ext-link-type="doi" xlink:href="10.7554/eLife.06057.019">http://dx.doi.org/10.7554/eLife.06057.019</ext-link></p></caption><table frame="hsides" rules="groups"><thead><tr><th/><th align="center">Observed</th><th align="center">Expected</th></tr></thead><tbody><tr><td colspan="3">NIPBL</td></tr><tr><td>&#8195;Synonymous</td><td align="center">58</td><td align="center">58.4</td></tr><tr><td>&#8195;Missense</td><td align="center">88</td><td align="center">160.9</td></tr><tr><td>&#8195;Loss of function</td><td align="center">0</td><td align="center">18.4</td></tr><tr><td colspan="3">Mau2</td></tr><tr><td>&#8195;Synonymous</td><td align="center">25</td><td align="center">26.6</td></tr><tr><td>&#8195;Missense</td><td align="center">13</td><td align="center">52.7</td></tr><tr><td>&#8195;Loss of function</td><td align="center">0</td><td align="center">3.8</td></tr></tbody></table></table-wrap>