<table-wrap xmlns:ali="http://www.niso.org/schemas/ali/1.0/" xmlns:xlink="http://www.w3.org/1999/xlink" id="table2" position="float"><object-id pub-id-type="doi">10.7554/eLife.34773.011</object-id><label>Table 2.</label><caption><title>Postcranial specimens used to approximate prey body size based on dimensions of the coprolite rib fragment.</title></caption><table frame="hsides" rules="groups"><thead><tr><th valign="bottom">Family</th><th valign="bottom">Genus</th><th valign="bottom">Species</th><th valign="bottom">Specimen number</th></tr></thead><tbody><tr><td valign="bottom">Antilocapridae</td><td valign="bottom">Antilocapra</td><td valign="bottom">americana</td><td valign="bottom">LACM 30482</td></tr><tr><td valign="bottom">Tayassuidae</td><td valign="bottom">Tayassu</td><td valign="bottom">pecari</td><td valign="bottom">LACM 86904</td></tr><tr><td valign="bottom">Camelidae</td><td valign="bottom">Lama</td><td valign="bottom">guanacoe</td><td valign="bottom">LACM 31328</td></tr><tr><td valign="bottom">Camelidae</td><td valign="bottom">Vicugna</td><td valign="bottom">vicugna</td><td valign="bottom">LACM 54706</td></tr><tr><td valign="bottom">Cervidae</td><td valign="bottom">Cervus</td><td valign="bottom">axis</td><td valign="bottom">LACM 529</td></tr><tr><td valign="bottom">Cervidae</td><td valign="bottom">Cervus</td><td valign="bottom">dama</td><td valign="bottom">LACM 30452</td></tr><tr><td valign="bottom">Cervidae</td><td valign="bottom">Cervus</td><td valign="bottom">dama</td><td valign="bottom">LACM 30876</td></tr><tr><td valign="bottom">Cervidae</td><td valign="bottom">Cervus</td><td valign="bottom">eldi</td><td valign="bottom">LACM 86095</td></tr><tr><td valign="bottom">Cervidae</td><td valign="bottom">Cervus</td><td valign="bottom">nippon</td><td valign="bottom">LACM 31069</td></tr><tr><td valign="bottom">Cervidae</td><td valign="bottom">Cervus</td><td valign="bottom">porcinus</td><td valign="bottom">LACM 85966</td></tr><tr><td valign="bottom">Cervidae</td><td valign="bottom">Cervus</td><td valign="bottom">timorensis</td><td valign="bottom">LACM 86012</td></tr><tr><td valign="bottom">Cervidae</td><td valign="bottom">Odocoileus</td><td valign="bottom">hemionus</td><td valign="bottom">LACM 307</td></tr><tr><td valign="bottom">Cervidae</td><td valign="bottom">Odocoileus</td><td valign="bottom">hemionus</td><td valign="bottom">LACM 30903</td></tr><tr><td valign="bottom">Cervidae</td><td valign="bottom">Odocoileus</td><td valign="bottom">virginianus</td><td valign="bottom">LACM 52442</td></tr></tbody></table></table-wrap>