<table-wrap xmlns:ali="http://www.niso.org/schemas/ali/1.0/" xmlns:xlink="http://www.w3.org/1999/xlink" id="table1" position="float"><object-id pub-id-type="doi">10.7554/eLife.37993.027</object-id><label>Table 1.</label><caption><title>Antibodies, chemicals, and plasmids used in this study</title></caption><table frame="hsides" rules="groups"><thead><tr><th>Reagent or resource</th><th>Source</th><th>Identifier</th></tr></thead><tbody><tr><td colspan="3" valign="top">Antibodies</td></tr><tr><td valign="top">Mouse monoclonal anti-UBE3A (clone E6AP-330)</td><td valign="top">Sigma-Aldrich</td><td valign="top">Cat#E8655</td></tr><tr><td valign="top">Rabbit monoclonal anti-p18</td><td valign="top">Cell Signaling Technology</td><td valign="top">Cat#8975</td></tr><tr><td valign="top">Rabbit polyclonal anti-p18</td><td valign="top">Sigma-Aldrich</td><td valign="top">Cat#HPA002997</td></tr><tr><td valign="top">Rabbit monoclonal anti-p14</td><td valign="top">Cell Signaling Technology</td><td valign="top">Cat#8145</td></tr><tr><td valign="top">Rabbit monoclonal anti-MP1</td><td valign="top">Cell Signaling Technology</td><td valign="top">Cat#8168</td></tr><tr><td valign="top">Rabbit monoclonal anti-LAMTOR4</td><td valign="top">Cell Signaling Technology</td><td valign="top">Cat#12284</td></tr><tr><td valign="top">Rabbit monoclonal anti-RagA</td><td valign="top">Cell Signaling Technology</td><td valign="top">Cat#4357</td></tr><tr><td valign="top">Rabbit monoclonal anti-RagB</td><td valign="top">Cell Signaling Technology</td><td valign="top">Cat#8150</td></tr><tr><td valign="top">Rabbit monoclonal anti-RagC</td><td valign="top">Cell Signaling Technology</td><td valign="top">Cat#5466</td></tr><tr><td valign="top">Mouse monoclonal anti-ubiquitin</td><td valign="top">Enzo Life Sciences</td><td valign="top">Cat#BML-PW8810</td></tr><tr><td valign="top">Mouse monoclonal anti-Flag</td><td valign="top">Sigma-Aldrich</td><td valign="top">Cat#F1804</td></tr><tr><td valign="top">Rat monoclonal anti-LAMP2</td><td valign="top">Abcam</td><td valign="top">Cat#ab13524</td></tr><tr><td valign="top">Mouse monoclonal anti-LAMP1</td><td valign="top">Abcam</td><td valign="top">Cat#ab25630</td></tr><tr><td valign="top">Rabbit polyclonal anti-p-mTOR Ser2448</td><td valign="top">Cell Signaling Technology</td><td valign="top">Cat#2971</td></tr><tr><td valign="top">Rabbit polyclonal anti-mTOR</td><td valign="top">Cell Signaling Technology</td><td valign="top">Cat#2972</td></tr><tr><td valign="top">Rabbit polyclonal anti-p-S6K1 Thr389</td><td valign="top">Cell Signaling Technology</td><td valign="top">Cat#9205</td></tr><tr><td valign="top">Rabbit polyclonal anti-S6K1</td><td valign="top">Cell Signaling Technology</td><td valign="top">Cat#9202</td></tr><tr><td valign="top">Rabbit polyclonal anti-p-S6 Ser240/244</td><td valign="top">Cell Signaling Technology</td><td valign="top">Cat#2215</td></tr><tr><td valign="top">Rabbit monoclonal anti-S6</td><td valign="top">Cell Signaling Technology</td><td valign="top">Cat#2217</td></tr><tr><td valign="top">Rabbit polyclonal anti-p-PKC</td><td valign="top">Cell Signaling Technology</td><td valign="top">Cat#9371</td></tr><tr><td valign="top">Rabbit polyclonal anti-PKC&#945;</td><td valign="top">Cell Signaling Technology</td><td valign="top">Cat#2056</td></tr><tr><td valign="top">Rabbit polyclonal anti-p-4EBP1 Ser65</td><td valign="top">Cell Signaling Technology</td><td valign="top">Cat#9451</td></tr><tr><td valign="top">Rabbit monoclonal anti-4EBP1</td><td valign="top">Cell Signaling Technology</td><td valign="top">Cat#9644</td></tr><tr><td valign="top">Rabbit monoclonal anti-p-AKT Ser473</td><td valign="top">Cell Signaling Technology</td><td valign="top">Cat#4060</td></tr><tr><td valign="top">Rabbit polyclonal anti-AKT</td><td valign="top">Cell Signaling Technology</td><td valign="top">Cat#9272</td></tr><tr><td valign="top">Mouse monoclonal anti-Raptor (clone 1H6.2)</td><td valign="top">EMD Millipore</td><td valign="top">Cat#05&#8211;1470</td></tr><tr><td valign="top">Rabbit polyclonal anti-Rictor</td><td valign="top">Bethyl Laboratories</td><td valign="top">Cat#A300-459A</td></tr><tr><td valign="top">Mouse monoclonal anti-NeuN (clone A60)</td><td valign="top">EMD Millipore</td><td valign="top">Cat#MAB377</td></tr><tr><td valign="top">Mouse monoclonal anti-PSD95 (clone 6G6-1C9)</td><td valign="top">Thermo Fisher Scientific</td><td valign="top">Cat#MA1-045</td></tr><tr><td valign="top">Mouse monoclonal anti-Cathepsin B (clone CA10)</td><td valign="top">EMD Millipore</td><td valign="top">Cat#IM27L</td></tr><tr><td valign="top">Rabbit monoclonal anti-COXIV</td><td valign="top">Cell Signaling Technology</td><td valign="top">Cat#4850</td></tr><tr><td valign="top">Chicken polyclonal anti-GFP</td><td valign="top">Thermo Fisher Scientific</td><td valign="top">Cat#A10262</td></tr><tr><td valign="top">Mouse monoclonal anti-GAPDH (clone 6C5)</td><td valign="top">EMD Millipore</td><td valign="top">Cat#MAB374</td></tr><tr><td valign="top">Mouse monoclonal anti-&#946;-actin (clone AC-15)</td><td valign="top">Sigma-Aldrich</td><td valign="top">Cat#A5441</td></tr><tr><td valign="top">Goat anti-rabbit IgG IRDye 680RD</td><td valign="top">LI-COR Biosciences</td><td valign="top">Cat#926&#8211;68071</td></tr><tr><td valign="top">Goat anti-mouse IgG IRDye 800CW</td><td valign="top">LI-COR Biosciences</td><td valign="top">Cat#926&#8211;32210</td></tr><tr><td valign="top">Goat anti-mouse IgG AlexaFluor 488</td><td valign="top">Invitrogen</td><td valign="top">Cat#A-11029</td></tr><tr><td valign="top">Goat anti-rabbit IgG AlexaFluor 594</td><td valign="top">Invitrogen</td><td valign="top">Cat#A-11037</td></tr><tr><td valign="top">Goat anti-rat IgG AlexaFluor 488</td><td valign="top">Invitrogen</td><td valign="top">Cat#A-11006</td></tr><tr><td valign="top">Goat anti-rat IgG AlexaFluor 594</td><td valign="top">Invitrogen</td><td valign="top">Cat#A-21209</td></tr><tr><td valign="top">Goat anti-rabbit IgG AlexaFluor 488</td><td valign="top">Invitrogen</td><td valign="top">Cat#A-11008</td></tr><tr><td valign="top">Goat anti-chicken IgY AlexaFluor 488</td><td valign="top">Invitrogen</td><td valign="top">Cat#A-11039</td></tr><tr><td valign="top">Goat anti-mouse IgG AlexaFluor 633</td><td valign="top">Invitrogen</td><td valign="top">Cat#A-21052</td></tr><tr><td valign="top">Goat anti-rabbit IgG AlexaFluor 633</td><td valign="top">Invitrogen</td><td valign="top">Cat#A-21070</td></tr><tr><td colspan="3" valign="top">Chemicals</td></tr><tr><td valign="top">MG132</td><td valign="top">EMD Millipore</td><td valign="top">Cat#474790</td></tr><tr><td valign="top">Bafilomycin A1</td><td valign="top">Sigma-Aldrich</td><td valign="top">Cat#B1793</td></tr><tr><td valign="top">MHY1485</td><td valign="top">EMD Millipore</td><td valign="top">Cat#500554</td></tr><tr><td colspan="3" valign="top">Recombinant DNA</td></tr><tr><td valign="top">HA-tagged wild-type Ube3a</td><td valign="top">(<xref ref-type="bibr" rid="bib45">Talis et al., 1998</xref>)</td><td valign="top">Addgene #8648</td></tr><tr><td valign="top">HA-tagged Ube3a-C833A</td><td valign="top">(<xref ref-type="bibr" rid="bib45">Talis et al., 1998</xref>)</td><td valign="top">Addgene #8649</td></tr><tr><td valign="top">HA-p18</td><td valign="top">(<xref ref-type="bibr" rid="bib1">Bar-Peled et al., 2012</xref>)</td><td valign="top">Addgene #42338</td></tr><tr><td valign="top">HA-p18G2A</td><td valign="top">(<xref ref-type="bibr" rid="bib1">Bar-Peled et al., 2012</xref>)</td><td valign="top">Addgene #42327</td></tr><tr><td valign="top">Flag-p18</td><td valign="top">(<xref ref-type="bibr" rid="bib1">Bar-Peled et al., 2012</xref>)</td><td valign="top">Addgene #42331</td></tr><tr><td valign="top">Flag-p18&#8710;K</td><td valign="top">This paper</td><td valign="top">N/A</td></tr><tr><td valign="top">Flag-p18K20R</td><td valign="top">This paper</td><td valign="top">N/A</td></tr><tr><td valign="top">Flag-p18K31R</td><td valign="top">This paper</td><td valign="top">N/A</td></tr><tr><td valign="top">Flag-p18K60R</td><td valign="top">This paper</td><td valign="top">N/A</td></tr><tr><td valign="top">Flag-p18K103/104R</td><td valign="top">This paper</td><td valign="top">N/A</td></tr><tr><td valign="top">Flag-p18K151R</td><td valign="top">This paper</td><td valign="top">N/A</td></tr><tr><td valign="top">His-ubiquitin</td><td valign="top">(<xref ref-type="bibr" rid="bib51">Young et al., 2011</xref>)</td><td valign="top">Addgene #31815</td></tr></tbody></table></table-wrap>