<table-wrap xmlns:ali="http://www.niso.org/schemas/ali/1.0/" xmlns:xlink="http://www.w3.org/1999/xlink" id="keyresource" position="anchor"><label>Key resources table</label><table frame="hsides" rules="groups"><thead><tr><th valign="bottom">Reagent type</th><th valign="bottom">Designation</th><th valign="bottom">Source or reference</th><th valign="bottom">Identifiers</th><th valign="bottom">Additional <break/>information</th></tr></thead><tbody><tr><td>Gene (<italic>D. melanogaste</italic>r)</td><td><italic>bantam</italic></td><td>NA</td><td>FLYB:FBgn0262451</td><td/></tr><tr><td>Gene (<italic>D. melanogaste</italic>r)</td><td><italic>coracle</italic></td><td>NA</td><td>FLYB:FBgn0010434</td><td/></tr><tr><td>Gene (<italic>D. melanogaste</italic>r)</td><td valign="bottom"><italic>dArf6</italic></td><td valign="bottom"/><td valign="bottom"/><td>FlyBase symbol: <break/>Arf51F</td></tr><tr><td>Gene (<italic>D. melanogaste</italic>r)</td><td><italic>Pis</italic></td><td>NA</td><td>FLYB:FBgn0030670</td><td/></tr><tr><td>Gene (<italic>D. melanogaste</italic>r)</td><td><italic>PI4KII</italic></td><td>NA</td><td>FLYB:FBgn0037339</td><td>FlyBase symbol: <break/>Pi4KII&#945;</td></tr><tr><td>Gene (<italic>D. melanogaste</italic>r)</td><td><italic>shg</italic></td><td>NA</td><td>FLYB:FBgn0003391</td><td/></tr><tr><td>Gene (<italic>D. melanogaste</italic>r)</td><td><italic>shi</italic></td><td>NA</td><td>FLYB:FBgn0003392</td><td/></tr><tr><td>Genetic reagent <break/>(<italic>D. melanogaster</italic>)</td><td><italic>w1118</italic></td><td>Bloomington <break/>Drosophila Stock <break/>Center</td><td>BDSC:5905; <break/>FLYB:FBal0018186</td><td>Parrish Lab stock</td></tr><tr><td>Genetic reagent <break/>(<italic>D. melanogaster</italic>)</td><td><italic>ppk-CD4-tdTomato</italic></td><td>Bloomington <break/>Drosophila Stock <break/>Center</td><td>BDSC:35844; <break/>FLYB:FBti0143430</td><td>FlyBase symbol: <break/>P{ppk-CD4-tdTomato}4a</td></tr><tr><td>Genetic reagent <break/>(<italic>D. melanogaster</italic>)</td><td><italic>ppk-CD4-tdTomato</italic></td><td>Bloomington <break/>Drosophila Stock <break/>Center</td><td>BDSC:35845; <break/>FLYB:FBti0143432</td><td>FlyBase symbol: <break/>P{ppk-CD4-tdTomato}10a</td></tr><tr><td><break/>Genetic reagent <break/>(<italic>D. melanogaster</italic>)</td><td><italic>Epidermal-Gal4</italic></td><td>PMID: 15269788</td><td>FLYB:FBti0072310</td><td>FlyBase symbol: <break/>P{GAL4}A58</td></tr><tr><td>Genetic reagent <break/>(<italic>D. melanogaster</italic>)</td><td><italic>elav-LexA</italic></td><td>Bloomington <break/>Drosophila Stock <break/>Center</td><td>BDSC:52676; <break/>FLYB:FBti0155565</td><td>FlyBase symbol: <break/>P{GMR27E08- <break/>lexA}attP40</td></tr><tr><td>Genetic reagent <break/>(<italic>D. melanogaster</italic>)</td><td><italic>lexAOP-CD4-tdTomato</italic></td><td>Bloomington <break/>Drosophila Stock <break/>Center</td><td>BDSC:77138; <break/>FLYB:FBti0195760</td><td>FlyBase symbol: <break/>P{13xLexAop2- <break/>CD4-tdTom}4</td></tr><tr><td>Genetic reagent <break/>(<italic>D. melanogaster</italic>)</td><td><italic>NompC-LexA</italic></td><td>Bloomington <break/>Drosophila Stock <break/>Center</td><td>BDSC:52240; <break/>FLYB:FBti0157008</td><td>FlyBase symbol: <break/>PBac{nompC-lexA::p65}VK00018</td></tr><tr><td>Genetic reagent <break/>(<italic>D. melanogaster</italic>)</td><td><italic>ppk-Gal4</italic></td><td>Bloomington <break/>Drosophila Stock <break/>Center</td><td>BDSC:32078; <break/>FLYB:FBti0127690</td><td>FlyBase symbol: <break/>P{ppk-GAL4.G}2</td></tr><tr><td>Genetic reagent <break/>(<italic>D. melanogaster</italic>) <break/></td><td><italic>ppk-Gal4</italic></td><td>Bloomington <break/>Drosophila Stock <break/>Center</td><td>BDSC:32079; <break/>FLYB:FBti0131208</td><td>FlyBase symbol: <break/>P{ppk-GAL4.G}3</td></tr><tr><td>Genetic reagent <break/>(<italic>D. melanogaster</italic>)</td><td><italic>21&#8211;7</italic> Gal4</td><td>PMID: 20696376</td><td>FLYB:FBti0157010</td><td>FlyBase symbol: <break/>P{GAL4}21&#8211;7</td></tr><tr><td>Genetic reagent <break/>(<italic>D. melanogaster</italic>)</td><td><italic>98b-Gal4</italic></td><td>PMID: 26063572</td><td>FLYB:FBti0169386</td><td>FlyBase symbol: <break/>P{GAL4}98b</td></tr><tr><td>Genetic reagent <break/>(<italic>D. melanogaster</italic>)</td><td><italic>GMR37B02-Gal4</italic></td><td>PMID: 20697123</td><td>FLYB: FBti0135266</td><td>FlyBase symbol: <break/>P{GMR37B02-GAL4}attP2</td></tr><tr><td>Genetic reagent <break/>(<italic>D. melanogaster</italic>)</td><td><italic>UAS-rpr</italic></td><td>Bloomington <break/>Drosophila Stock <break/>Center</td><td>BDSC:5824; <break/>FLYB:FBti0016094</td><td>FlyBase symbol: <break/>P{UAS-rpr.C}14</td></tr><tr><td>Genetic reagent <break/>(<italic>D. melanogaster</italic>)</td><td><italic>UAS-PIS(RNAi)</italic></td><td>Bloomington <break/>Drosophila Stock <break/>Center</td><td>BDSC:29383; <break/>FLYB:FBti0129011</td><td>FlyBase symbol: <break/>P{TRiP.JF03315}attP2</td></tr><tr><td>Genetic reagent <break/>(<italic>D. melanogaster</italic>)</td><td><italic>UAS-PI4KII(RNAi)</italic></td><td>Bloomington <break/>Drosophila Stock <break/>Center</td><td>BDSC:38242; <break/>FLYB:FBti0144268</td><td>FlyBase symbol: <break/>P{TRiP.GL00179}attP2</td></tr><tr><td>Genetic reagent <break/>(<italic>D. melanogaster</italic>)</td><td><italic>UAS-cora(RNAi)</italic></td><td>Bloomington <break/>Drosophila Stock <break/>Center</td><td>BDSC:51845; <break/>FLYB:FBti0157811</td><td>FlyBase symbol: <break/>P{TRiP.HMC03418}attP40</td></tr><tr><td>Genetic reagent <break/>(<italic>D. melanogaster</italic>)</td><td><italic>UAS-shg(RNAi)</italic></td><td>Bloomington <break/>Drosophila Stock <break/>Center</td><td>BDSC:32904; <break/>FLYB:FBti0140407</td><td>FlyBase symbol: <break/>P{TRiP.HMS00693}attP2</td></tr><tr><td>Genetic reagent <break/>(<italic>D. melanogaster</italic>)</td><td><italic>UAS-shits</italic></td><td>Bloomington <break/>Drosophila Stock <break/>Center</td><td>BDSC:44222; <break/>FLYB:FBti0151794</td><td>FlyBase symbol: <break/>P{UAS-shits1.K}3</td></tr><tr><td>Genetic reagent <break/>(<italic>D. melanogaster</italic>)</td><td><italic>UAS-shiDN</italic></td><td>Bloomington <break/>Drosophila Stock <break/>Center</td><td>BDSC:5811; <break/>FLYB:FBti0016096</td><td>FlyBase symbol: <break/>P{UAS-shi.K44A}4&#8211;1</td></tr><tr><td>Genetic reagent <break/>(<italic>D. melanogaster</italic>)</td><td><italic>UAS-mys</italic></td><td>PMID: 10572057</td><td>FLYB:FBal0102506</td><td>FlyBase symbol: <break/>mysUAS.cDa</td></tr><tr><td>Genetic reagent <break/>(<italic>D. melanogaster</italic>)</td><td><italic>UAS-mew</italic></td><td>PMID: 9250662</td><td>FLYB:FBal0062567</td><td>FlyBase symbol: <break/>mewUAS.cMBa</td></tr><tr><td>Genetic reagent <break/>(<italic>D. melanogaster</italic>)</td><td><italic>UAS-Kir2.1-GFP</italic></td><td>Bloomington <break/>Drosophila Stock <break/>Center</td><td>BDSC:6596; <break/>FLYB:FBti0017551</td><td>FlyBase symbol: <break/>P{UAS-Hsap\KCNJ2.EGFP}1</td></tr><tr><td>Genetic reagent <break/>(<italic>D. melanogaster</italic>)</td><td><italic>Cha<sup>7.4kb</sup>-Gal80</italic></td><td>PMID: 19531155</td><td>FLYB:FBtp0089195</td><td>FlyBase symbol: <break/>P{ChAT.7.4kb-Gal80}</td></tr><tr><td>Genetic reagent <break/>(<italic>D. melanogaster</italic>)</td><td><italic>bantam&#916;1</italic></td><td>PMID: 12196398</td><td>FLYB:FBab0029992</td><td>FlyBase symbol: <break/>Df(3L)ban&#916;1</td></tr><tr><td>Genetic reagent <break/>(<italic>D. melanogaster</italic>)</td><td><italic>UAS-CD4-tdGFP</italic></td><td>Bloomington <break/>Drosophila Stock <break/>Center</td><td>BDSC:35836; <break/>FLYB:FBti0143423</td><td>FlyBase symbol: <break/>PBac{UAS-CD4-tdGFP}VK00033</td></tr><tr><td>Genetic reagent <break/>(<italic>D. melanogaster</italic>)</td><td><italic>UAS-mCD8-GFP</italic></td><td>Bloomington <break/>Drosophila Stock <break/>Center</td><td>BDSC:5137; <break/>FLYB:FBti0012685</td><td>FlyBase symbol: <break/>P{UAS-mCD8::GFP.L}LL5</td></tr><tr><td>Genetic reagent <break/>(<italic>D. melanogaster</italic>)</td><td><italic>UAS-myr-GFP</italic></td><td>Bloomington <break/>Drosophila Stock <break/>Center</td><td>BDSC:32198; <break/>FLYB:FBti0131964</td><td>FlyBase symbol: <break/>P{10XUAS-IVS-myr::GFP}attP40</td></tr><tr><td>Genetic reagent <break/>(<italic>D. melanogaster</italic>)</td><td><italic>UAS-Asap-GFP</italic></td><td>Bloomington <break/>Drosophila Stock <break/>Center</td><td>BDSC:65849; <break/>FLYB:FBti0183078</td><td>FlyBase symbol: <break/>P{UASp-Asap.GFP}attP2</td></tr><tr><td>Genetic reagent <break/>(<italic>D. melanogaster</italic>)</td><td><italic>UAS-Dl-GFP</italic></td><td>Bloomington <break/>Drosophila Stock <break/>Center</td><td>BDSC:8610; <break/>FLYB:FBti0058796</td><td>FlyBase symbol: <break/>P{UAS-Dl::GFP}DA53</td></tr><tr><td>Genetic reagent <break/>(<italic>D. melanogaster</italic>)</td><td><italic>UAS-CG10702-GFP</italic></td><td>Bloomington <break/>Drosophila Stock <break/>Center</td><td>BDSC:65857; <break/>FLYB:FBti0183086</td><td>FlyBase symbol: <break/>P{UASp-CG10702.GFP}attP2</td></tr><tr><td>Genetic reagent <break/>(<italic>D. melanogaster</italic>)</td><td><italic>UAS-Dlg5-GFP</italic></td><td>Bloomington <break/>Drosophila Stock <break/>Center</td><td>BDSC:30928; <break/>FLYB:FBti0130055</td><td>FlyBase symbol: <break/>P{UAS-Dlg5.GFP}2</td></tr><tr><td>Genetic reagent <break/>(<italic>D. melanogaster</italic>)</td><td><italic>Sdc-CPTI002578</italic></td><td>Kyoto Drosophila <break/>Genomics and Genetics <break/>Resources</td><td>Kyoto:115306; <break/>FLYB:FBal0261862</td><td>FlyBase symbol: <break/>SdcCPTI002578</td></tr><tr><td>Genetic reagent <break/>(<italic>D. melanogaster</italic>)</td><td><italic>UAS-2xOsh2PH-GFP</italic></td><td>Bloomington <break/>Drosophila Stock <break/>Center</td><td>BDSC:57353; <break/>FLYB:FBti0162453</td><td>FlyBase symbol: <break/>P{UAS-2xOsh2PH-GFP}attP2</td></tr><tr><td>Genetic reagent <break/>(<italic>D. melanogaster</italic>)</td><td><italic>UAS-PLC&#948;-PH-GFP</italic></td><td>Bloomington <break/>Drosophila Stock <break/>Center</td><td>BDSC:39693; <break/>FLYB:FBti0148832</td><td>FlyBase symbol: <break/>P{UAS-PLC&#948;-PH-EGFP}3</td></tr><tr><td>Genetic reagent <break/>(<italic>D. melanogaster</italic>)</td><td><italic>UAS-PLCD1-PH-Cerulean</italic></td><td>Bloomington <break/>Drosophila Stock <break/>Center</td><td>BDSC:30895; <break/>FLYB:FBti0129991</td><td>FlyBase symbol: <break/>P{UASp-PLCD1PH.Cerulean}2</td></tr><tr><td>Genetic reagent <break/>(<italic>D. melanogaster</italic>)</td><td><italic>UAS-PLC&#948;-PH-GFP (S39R)</italic></td><td>Bloomington <break/>Drosophila Stock <break/>Center</td><td>BDSC:39694; <break/>FLYB:FBti0148833</td><td>FlyBase symbol: <break/>P{UAS-PLC&#948;-PH. <break/>S39R-EGFP}3</td></tr><tr><td>Genetic reagent <break/>(<italic>D. melanogaster</italic>)</td><td><italic>UAS-step-GFP</italic></td><td>Bloomington <break/>Drosophila Stock <break/>Center</td><td>BDSC:65862; <break/>FLYB:FBti0183091</td><td>FlyBase symbol: <break/>P{UASp-step.EGFP}attP2</td></tr><tr><td>Genetic reagent <break/>(<italic>D. melanogaster</italic>)</td><td><italic>UAS-GFP-myc-2xFYVE</italic></td><td>Bloomington <break/>Drosophila Stock <break/>Center</td><td>BDSC:42712; <break/>FLYB:FBti0147756</td><td>FlyBase symbol: <break/>P{UAS-GFP-myc-2xFYVE}2</td></tr><tr><td>Genetic reagent <break/>(<italic>D. melanogaster</italic>)</td><td><italic>UAS-Arf51F-GFP</italic></td><td>Bloomington <break/>Drosophila Stock <break/>Center</td><td>BDSC:65867; <break/>FLYB:FBti0183094</td><td>FlyBase symbol: <break/>P{UASp-Arf51F.GFP}attP2</td></tr><tr><td>Genetic reagent <break/>(<italic>D. melanogaster</italic>)</td><td><italic>UAS-Arf79F-GFP</italic></td><td>Bloomington <break/>Drosophila Stock <break/>Center</td><td>BDSC:65850; <break/>FLYB:FBti0183079</td><td>FlyBase symbol: <break/>P{UASp-Arf79F.GFP}attP3</td></tr><tr><td>Genetic reagent <break/>(<italic>D. melanogaster</italic>)</td><td><italic>UAS-Arf102F-GFP</italic></td><td>Bloomington <break/>Drosophila Stock <break/>Center</td><td>BDSC:65866; <break/>FLYB:FBti0183075</td><td>FlyBase symbol: <break/>P{UASp-Arf102F.GFP}attP4</td></tr><tr><td>Genetic reagent <break/>(<italic>D. melanogaster</italic>)</td><td><italic>UAS-Arl4-GFP</italic></td><td>Bloomington <break/>Drosophila Stock <break/>Center</td><td>BDSC:65868; <break/>FLYB:FBti0183092</td><td>FlyBase symbol: <break/>P{UASp-Arl4.GFP}attP5</td></tr><tr><td>Genetic reagent <break/>(<italic>D. melanogaster</italic>)</td><td><italic>UAS-Clc-GFP</italic></td><td>Bloomington <break/>Drosophila Stock <break/>Center</td><td>BDSC:7109; <break/>FLYB:FBti0027887</td><td>FlyBase symbol: <break/>P{UAS-EGFP-Clc}5</td></tr><tr><td>Genetic reagent <break/>(<italic>D. melanogaster</italic>)</td><td><italic>UAS-gamma-cop-GFP</italic></td><td>Bloomington <break/>Drosophila Stock <break/>Center</td><td>BDSC:29711; <break/>FLYB:FBti0128586</td><td>FlyBase symbol: <break/>P{UASp-&#947;COP.EGFP}3</td></tr><tr><td>Genetic reagent <break/>(<italic>D. melanogaster</italic>)</td><td><italic>UAS-YFP-Rab4</italic></td><td>Bloomington <break/>Drosophila Stock <break/>Center</td><td>BDSC:9767; <break/>FLYB:FBti0100783</td><td>FlyBase symbol: <break/>P{UASp-YFP.Rab4}Sap-r32</td></tr><tr><td>Genetic reagent <break/>(<italic>D. melanogaster</italic>)</td><td><italic>UAS-YFP-Rab-5</italic></td><td>Bloomington <break/>Drosophila Stock <break/>Center</td><td>BDSC:24616; <break/>FLYB:FBti0100788</td><td>FlyBase symbol: <break/>P{UASp-YFP.Rab5}02</td></tr><tr><td>Genetic reagent <break/>(<italic>D. melanogaster</italic>) <break/> <break/><break/></td><td><italic>UAS-GFP-Rab-7</italic></td><td>Bloomington <break/>Drosophila Stock <break/>Center <break/></td><td>BDSC:42705; <break/>FLYB:FBti0150335</td><td>FlyBase symbol: <break/>P{UASp-YFP.Rab7}2</td></tr><tr><td><break/>Genetic reagent <break/>(<italic>D. melanogaster</italic>)</td><td><italic>UAS-YFP-Rab11</italic></td><td>Bloomington <break/>Drosophila Stock <break/>Center</td><td>BDSC:50782; <break/>FLYB:FBti0152903</td><td>FlyBase symbol: <break/>P{UASp-YFP.Rab11}3</td></tr><tr><td>Genetic reagent <break/>(<italic>D. melanogaster</italic>)</td><td><italic>UAS-YFP-Rab-21</italic></td><td>Bloomington <break/>Drosophila Stock <break/>Center</td><td>BDSC:23242; <break/>FLYB:FBti0100844</td><td>FlyBase symbol: <break/>P{UAST-YFP.Rab21}smog04</td></tr><tr><td>Genetic reagent <break/>(<italic>D. melanogaster</italic>)</td><td><italic>UAS-YFP-Rab35</italic></td><td>Bloomington <break/>Drosophila Stock <break/>Center</td><td>BDSC:9821; <break/>FLYB:FBti0100873</td><td>FlyBase symbol: <break/>P{UASp-YFP.Rab35}15</td></tr><tr><td>Genetic reagent <break/>(<italic>D. melanogaster</italic>)</td><td><italic>UAS-spin-RFP</italic></td><td>Bloomington <break/>Drosophila Stock <break/>Center</td><td>BDSC:42716; <break/>FLYB:FBti0147756</td><td>FlyBase symbol: <break/>P{UAS-GFP-myc-2xFYVE}2</td></tr><tr><td>Genetic reagent <break/>(<italic>D. melanogaster</italic>)</td><td><italic>UAS-Shrub-GFP</italic></td><td>Bloomington <break/>Drosophila Stock <break/>Center</td><td>BDSC:32559; <break/>FLYB:FBti0131611</td><td>FlyBase symbol: <break/>P{UAS-shrb-GFP}2</td></tr><tr><td>Genetic reagent <break/>(<italic>D. melanogaster</italic>)</td><td><italic>UAS-dia-GFP</italic></td><td>Bloomington <break/>Drosophila Stock <break/>Center</td><td>BDSC:56751; <break/>FLYB:FBti0161167</td><td>FlyBase symbol: <break/>P{UASp-dia.EGFP}2</td></tr><tr><td>Genetic reagent <break/>(<italic>D. melanogaster</italic>)</td><td><italic>UAS-EndoA-GFP</italic></td><td>This paper</td><td/><td>Created by injecting <break/><italic>pJFRC7-EndoA-GFP</italic> <break/>DNA into flies with <break/>the <italic>attP2</italic> docking site</td></tr><tr><td>Genetic reagent <break/>(<italic>D. melanogaster</italic>)</td><td><italic>UAS-EndoB-GFP</italic></td><td>This paper</td><td/><td>Created by injecting <break/>pJFRC7-EndoB-GFP <break/>DNA into flies with <break/>the attP2 docking site</td></tr><tr><td>Genetic reagent <break/>(<italic>D. melanogaster</italic>)</td><td><italic>UAS-Cip4-GFP</italic></td><td>PMID: 19716703</td><td>FLYB:FBtp0055642</td><td>FlyBase symbol: <break/>P{UAS-Cip4.EGFP}</td></tr><tr><td>Genetic reagent <break/>(<italic>D. melanogaster</italic>)</td><td><italic>UAS-Arm-GFP</italic></td><td>Bloomington <break/>Drosophila Stock <break/>Center</td><td>BDSC:58725; <break/>FLYB:FBti0164941</td><td>FlyBase symbol: <break/>M{UASp-arm.mGFP6}ZH-86Fb</td></tr><tr><td>Genetic reagent <break/>(<italic>D. melanogaster</italic>)</td><td><italic>UAS-shg-GFP</italic></td><td>Bloomington <break/>Drosophila Stock <break/>Center</td><td>BDSC:58445; <break/>FLYB:FBti0164810</td><td>FlyBase symbol: <break/>P{UASp-shg.GFP}5B</td></tr><tr><td>Genetic reagent <break/>(<italic>D. melanogaster</italic>)</td><td><italic>UAS-baz-GFP</italic></td><td>Bloomington <break/>Drosophila Stock <break/>Center</td><td>BDSC:65845; <break/>FLYB:FBti0183077</td><td>FlyBase symbol: <break/>P{UASp-baz.C.GFP}attP2</td></tr><tr><td>Genetic reagent <break/>(<italic>D. melanogaster</italic>)</td><td><italic>UAS-Dlg-GFP</italic></td><td>Bloomington <break/>Drosophila Stock <break/>Center</td><td>BDSC:8610; <break/>FLYB:FBti0058796</td><td>FlyBase symbol: <break/>P{UAS-Dl::GFP}DA53</td></tr><tr><td>Genetic reagent <break/>(<italic>D. melanogaster</italic>)</td><td><italic>edGFP exon trap</italic></td><td>Kyoto Drosophila <break/>Genomics and <break/>Genetics Resources</td><td>Kyoto:115114; <break/>FLYB:FBti0144023</td><td>FlyBase symbol: <break/>PBac{602 .P.SVS-1}edCPTI000616</td></tr><tr><td>Genetic reagent <break/>(<italic>D. melanogaster</italic>)</td><td><italic>Nrg-GFP</italic></td><td>Bloomington <break/>Drosophila Stock <break/>Center</td><td>BDSC:6844; <break/>FLYB:FBti0027855</td><td>FlyBase symbol: <break/>P{PTT-GA}NrgG00305</td></tr><tr><td>Genetic reagent <break/>(<italic>D. melanogaster</italic>)</td><td><italic>NrxIV-GFP</italic></td><td>Bloomington <break/>Drosophila Stock <break/>Center</td><td>BDSC:50798; <break/>FLYB:FBti0099828</td><td>FlyBase symbol: <break/>P{PTT-GA}Nrx-IVCA06597</td></tr><tr><td>Genetic reagent <break/>(<italic>D. melanogaster</italic>)</td><td><italic>UAS-actin-GFP</italic></td><td>Bloomington <break/>Drosophila Stock <break/>Center</td><td>BDSC:9258; <break/>FLYB:FBti0072618</td><td>FlyBase symbol: <break/>P{UASp-GFP.Act5C}2&#8211;1</td></tr><tr><td>Genetic reagent <break/>(<italic>D. melanogaster</italic>)</td><td><italic>UAS-GMA-GFP</italic></td><td>Bloomington <break/>Drosophila Stock <break/>Center</td><td>BDSC:31776; <break/>FLYB:FBti0131132</td><td>FlyBase symbol: <break/>P{UAS-GMA}3</td></tr><tr><td>Genetic reagent <break/>(<italic>D. melanogaster</italic>)</td><td><italic>UAS-APC2-GFP</italic></td><td>Bloomington <break/>Drosophila Stock <break/>Center</td><td>BDSC:8815; <break/>FLYB:FBti0072923</td><td>FlyBase symbol: <break/>P{UAS-Apc2.GFP}3</td></tr><tr><td>Genetic reagent <break/>(<italic>D. melanogaster</italic>)</td><td><italic>UAS-LifeAct.mGFP</italic></td><td>Bloomington <break/>Drosophila Stock <break/>Center</td><td>BDSC:58717; <break/>FLYB:FBti0164965</td><td>FlyBase symbol: <break/>M{UASp-LifeAct.mGFP6}ZH-2A</td></tr><tr><td>Genetic reagent <break/>(<italic>D. melanogaster</italic>)</td><td><italic>UAS-Arp3-GFP</italic></td><td>Bloomington <break/>Drosophila Stock <break/>Center</td><td>BDSC:39722; <break/>FLYB:FBti0148835</td><td>FlyBase symbol: <break/>P{UASp-Arp3.GFP}3</td></tr><tr><td>Genetic reagent <break/>(<italic>D. melanogaster</italic>)</td><td><italic>UAS-Arpc1-GFP</italic></td><td>Bloomington <break/>Drosophila Stock <break/>Center</td><td>BDSC:26692; <break/>FLYB:FBti0114937</td><td>FlyBase symbol: <break/>P{UASp-Arpc1.GFP}1</td></tr><tr><td>Genetic reagent <break/>(<italic>D. melanogaster</italic>)</td><td><italic>UAS-capu-GFP</italic></td><td>Bloomington <break/>Drosophila Stock <break/>Center</td><td>BDSC:24764; <break/>FLYB:FBti0100538</td><td>FlyBase symbol: <break/>P{UASp-capu.GFP}20</td></tr><tr><td>Genetic reagent <break/>(<italic>D. melanogaster</italic>)</td><td><italic>UAS-dpod1-GFP</italic></td><td>Bloomington <break/>Drosophila Stock <break/>Center</td><td>BDSC:8800; <break/>FLYB:FBti0072921</td><td>FlyBase symbol: <break/>P{UAS-pod1.GFPmyc}3</td></tr><tr><td>Genetic reagent <break/>(<italic>D. melanogaster</italic>)</td><td><italic>UAS-Pak-GFP</italic></td><td>Bloomington <break/>Drosophila Stock <break/>Center</td><td>BDSC:52299; <break/>FLYB:FBti0155014</td><td>FlyBase symbol: <break/>P{UASp-GFP-Pak1}300</td></tr><tr><td>Genetic reagent <break/>(<italic>D. melanogaster</italic>)</td><td><italic>UAS-Rho1-GFP</italic></td><td>Bloomington <break/>Drosophila Stock <break/>Center</td><td>BDSC:9393; <break/>FLYB:FBti0074447</td><td>FlyBase symbol: <break/>P{UASp-GFP.Rho1}6</td></tr><tr><td>Genetic reagent <break/>(<italic>D. melanogaster</italic>)</td><td><italic>UAS-Rok-GFP</italic></td><td>Bloomington <break/>Drosophila Stock <break/>Center</td><td>BDSC:52290; <break/>FLYB:FBti0155000</td><td>FlyBase symbol: <break/>P{UASp-Rok.RBD-GFP}30</td></tr><tr><td>Genetic reagent <break/>(<italic>D. melanogaster</italic>)</td><td><italic>UAS-shot-GFP</italic></td><td>Bloomington <break/>Drosophila Stock <break/>Center</td><td>BDSC:29044; <break/>FLYB:FBti0127943</td><td>FlyBase symbol: <break/>P{UAS-shot.L(A)-GFP}1</td></tr><tr><td>Genetic reagent <break/>(<italic>D. melanogaster</italic>)</td><td><italic>UAS-GFP-blr</italic></td><td>Bloomington <break/>Drosophila Stock <break/>Center</td><td>BDSC:8659; <break/>FLYB:FBti0064611</td><td>FlyBase symbol: <break/>P{UAS-GFP.BLR}3</td></tr><tr><td><break/>Genetic reagent <break/>(<italic>D. melanogaster</italic>)</td><td><italic>UAS-spir-GFP</italic></td><td>Bloomington <break/>Drosophila Stock <break/>Center</td><td>BDSC:8820; <break/>FLYB:FBti0072893</td><td>FlyBase symbol: <break/>P{UAS-spir.L.GFP}3</td></tr><tr><td>Genetic reagent <break/>(<italic>D. melanogaster</italic>)</td><td><italic>UAS-GFP-sstn</italic></td><td>Bloomington <break/>Drosophila Stock <break/>Center</td><td>BDSC:65863; <break/>FLYB:FBti0183072</td><td>FlyBase symbol: <break/>P{UASp-GFP-sstn}attP40</td></tr><tr><td>Genetic reagent <break/>(<italic>D. melanogaster</italic>)</td><td><italic>UAS-alpha-tubulin84B-GFP</italic></td><td>Bloomington <break/>Drosophila Stock <break/>Center</td><td>BDSC:7373; <break/>FLYB:FBti0038034</td><td>FlyBase symbol: <break/>P{UASp-GFPS65C- <break/>&#945;Tub84B}3</td></tr><tr><td>Genetic reagent <break/>(<italic>D. melanogaster</italic>)</td><td><italic>UAS-EB1-GFP</italic></td><td>Bloomington <break/>Drosophila Stock <break/>Center</td><td>BDSC:35512; <break/>FLYB:FBti0141213</td><td>FlyBase symbol: <break/>P{UAS-EB1-GFP}3</td></tr><tr><td>Genetic reagent <break/>(<italic>D. melanogaster</italic>) <break/></td><td><italic>UAS-hook-GFP</italic></td><td>Bloomington <break/>Drosophila Stock <break/>Center</td><td>BDSC:65858; <break/>FLYB:FBti183087</td><td>FlyBase symbol: <break/>P{UASp-hook.GFP}attP2</td></tr><tr><td>Genetic reagent <break/>(<italic>D. melanogaster</italic>)</td><td><italic>UAS-jar-GFP</italic></td><td>Bloomington <break/>Drosophila Stock <break/>Center</td><td>BDSC:67606; <break/>FLYB:FBti0186539</td><td>FlyBase symbol: <break/>P{UAS-jar.GFP}2</td></tr><tr><td>Genetic reagent <break/>(<italic>D. melanogaster</italic>)</td><td><italic>UAS-Khc-GFP</italic></td><td>Bloomington <break/>Drosophila Stock <break/>Center</td><td>BDSC:9648; <break/>FLYB:FBti0076674</td><td>FlyBase symbol: <break/>P{UAS-Khc.EGFP}2</td></tr><tr><td>Genetic reagent <break/>(<italic>D. melanogaster</italic>)</td><td><italic>UAS-GFP-Myo10A</italic></td><td>Bloomington <break/>Drosophila Stock <break/>Center</td><td>BDSC:24781; <break/>FLYB:FBti0100569</td><td>FlyBase symbol: <break/>P{UASp-Myo10A.GFP}20</td></tr><tr><td>Genetic reagent <break/>(<italic>D. melanogaster</italic>)</td><td><italic>UAS-GFP-Myo31DF</italic></td><td>Bloomington <break/>Drosophila Stock <break/>Center</td><td>BDSC:1521; <break/>FLYB:FBti0003040</td><td>FlyBase symbol: <break/>P{UAS-GFP.S65T} <break/>Myo31DFT2</td></tr><tr><td>Genetic reagent <break/>(<italic>D. melanogaster</italic>)</td><td><italic>UAS-GFP-NinaC</italic></td><td>Bloomington <break/>Drosophila Stock <break/>Center</td><td>BDSC:43347; <break/>FLYB:FBti0151777</td><td>FlyBase symbol: <break/>P{UAS-GFP-ninaC}2</td></tr><tr><td>Genetic reagent <break/>(<italic>D. melanogaster</italic>)</td><td><italic>UAS-GFP-DCTN1-p150</italic></td><td>Bloomington <break/>Drosophila Stock <break/>Center</td><td>BDSC:29982; <break/>FLYB:FBti0128481</td><td>FlyBase symbol: <break/>P{UAS-GFP.DCTN1 <break/>-p150}2</td></tr><tr><td>Genetic reagent <break/>(<italic>D. melanogaster</italic>)</td><td><italic>UAS-Unc104-GFP</italic></td><td>Bloomington <break/>Drosophila Stock <break/>Center</td><td>BDSC:24786; <break/>FLYB:FBti0100934</td><td>FlyBase symbol: <break/>P{UAS-unc-104.GFP.RVB}1</td></tr><tr><td><break/>Genetic reagent <break/>(<italic>D. melanogaster</italic>) <break/></td><td><italic>UAS-Supervillin-GFP</italic></td><td>Bloomington <break/>Drosophila Stock <break/>Center</td><td>BDSC:66165; <break/>FLYB:FBti0183648</td><td>FlyBase symbol: <break/>P{UASp-GFP.Svil}attP2</td></tr><tr><td>Genetic reagent <break/>(<italic>D. melanogaster</italic>)</td><td><italic>UAS-GFP-RhoGAP19D</italic></td><td>Bloomington <break/>Drosophila Stock <break/>Center</td><td>BDSC:66167; <break/>FLYB:FBti0183650</td><td>FlyBase symbol: <break/>P{UASp-GFP.RhoGAP19D}attP2</td></tr><tr><td>Genetic reagent <break/>(<italic>D. melanogaster</italic>)</td><td><italic>UAS-Par6-GFP</italic></td><td>Bloomington <break/>Drosophila Stock <break/>Center</td><td>BDSC:65847; <break/>FLYB:FBti0183076</td><td>FlyBase symbol: <break/>P{UAS-par-6.GFP}2</td></tr><tr><td>Genetic reagent <break/>(<italic>D. melanogaster</italic>)</td><td><italic>UAS-fy-GFP</italic></td><td>Bloomington <break/>Drosophila Stock <break/>Center</td><td>BDSC:66513; <break/>FLYB:FBti0184640</td><td>FlyBase symbol: <break/>P{UAS-fy.GFP}3</td></tr><tr><td>Genetic reagent <break/>(<italic>D. melanogaster</italic>)</td><td><italic>UAS-sds22.GFP</italic></td><td>Bloomington <break/>Drosophila Stock <break/>Center</td><td>BDSC:65851; <break/>FLYB:FBti0183080</td><td>FlyBase symbol: <break/>P{UASp-sds22.GFP}attP2</td></tr><tr><td>Genetic reagent <break/>(<italic>D. melanogaster</italic>)</td><td><italic>UAS-EGFP (cytosolic)</italic></td><td>Bloomington <break/>Drosophila Stock <break/>Center</td><td>BDSC:5431; <break/>FLYB:FBti0013987</td><td>FlyBase symbol: <break/>P{UAS-EGFP}5a.2</td></tr><tr><td>Genetic reagent <break/>(<italic>D. melanogaster</italic>) <break/></td><td><italic>UAS-mito-GFP</italic></td><td>Bloomington <break/>Drosophila Stock <break/>Center</td><td>BDSC:8443; <break/>FLYB:FBti0040804</td><td>FlyBase symbol: <break/>P{UAS-mito-HA-GFP.AP}3</td></tr><tr><td>Genetic reagent <break/>(<italic>D. melanogaster</italic>)</td><td><italic>UAS-GFP-Golgi</italic></td><td>Bloomington <break/>Drosophila Stock <break/>Center</td><td>BDSC:31422; <break/>FLYB:FBti0129989</td><td>FlyBase symbol: <break/>P{UASp-GFP.Golgi}14</td></tr><tr><td>Genetic reagent <break/>(<italic>D. melanogaster</italic>)</td><td><italic>UAS-GFP-KDEL</italic></td><td>Bloomington <break/>Drosophila Stock <break/>Center</td><td>BDSC:9898; <break/>FLYB:FBti0076567</td><td>FlyBase symbol: <break/>P{UAS-GFP.KDEL}11.1</td></tr><tr><td>Genetic reagent <break/>(<italic>D. melanogaster</italic>)</td><td><italic>UAS-GFP.SKL</italic></td><td>Bloomington <break/>Drosophila Stock <break/>Center</td><td>BDSC:28881; <break/>FLYB:FBti0127932</td><td>FlyBase symbol: <break/>P{UAS-GFP.SKL}2</td></tr><tr><td>Genetic reagent <break/>(<italic>D. melanogaster</italic>)</td><td><italic>UAS-eGFP-Atg5</italic></td><td>Bloomington <break/>Drosophila Stock <break/>Center</td><td>BDSC:59848; <break/>FLYB:FBti0072907</td><td>FlyBase symbol: <break/>P{UASp-eGFP-drAtg5}16</td></tr><tr><td>Genetic reagent <break/>(<italic>D. melanogaster</italic>)</td><td><italic>UAS-Atg8-GFP</italic></td><td>Bloomington <break/>Drosophila Stock <break/>Center</td><td>BDSC:52005; <break/>FLYB:FBti0154554</td><td>FlyBase symbol: <break/>P{UAS-Atg8a.GFP}2</td></tr><tr><td><break/>Genetic reagent <break/>(<italic>D. melanogaster</italic>)</td><td><italic>UAS-GFP-LAMP</italic></td><td>Bloomington <break/>Drosophila Stock <break/>Center</td><td>BDSC:42714; <break/>FLYB:FBti0150347</td><td>FlyBase symbol: <break/>P{UAS-GFP-LAMP}2</td></tr><tr><td>Genetic reagent <break/>(<italic>D. melanogaster</italic>) <break/></td><td><italic>UAS-Aplip-GFP</italic></td><td>Bloomington <break/>Drosophila Stock <break/>Center</td><td>BDSC:24634; <break/>FLYB:FBti0100247</td><td>FlyBase symbol: <break/>P{UASp-Aplip1.EGFP}3</td></tr><tr><td>Genetic reagent <break/>(<italic>D. melanogaster</italic>)</td><td><italic>UAS-hiw-GFP</italic></td><td>Bloomington <break/>Drosophila Stock <break/>Center</td><td>BDSC:51640; <break/>FLYB:FBti0164779</td><td>FlyBase symbol: <break/>P{UAS-GFP-hiw}B</td></tr><tr><td>Genetic reagent <break/>(<italic>D. melanogaster</italic>)</td><td><italic>UAS-src-EGFP</italic></td><td>Bloomington <break/>Drosophila Stock <break/>Center</td><td>BDSC:5429; <break/>FLYB:FBti0013989</td><td>FlyBase symbol: <break/>P{UAS-srcEGFP}M7A</td></tr><tr><td>Genetic reagent <break/>(<italic>D. melanogaster</italic>)</td><td><italic>UAS-bsk-GFP</italic></td><td>Bloomington <break/>Drosophila Stock <break/>Center</td><td>BDSC:59267; <break/>FLYB:FBti0166949</td><td>FlyBase symbol: <break/>P{UAS-bsk.GFP}2</td></tr><tr><td>Genetic reagent <break/>(<italic>D. melanogaster</italic>)</td><td><italic>UAS-Dronc-GFP</italic></td><td>Bloomington <break/>Drosophila Stock <break/>Center</td><td>BDSC:56759; <break/>FLYB:FBti0161295</td><td>FlyBase symbol: <break/>P{UAS-Dronc.EGFP}2</td></tr><tr><td>Genetic reagent <break/>(<italic>D. melanogaster</italic>)</td><td><italic>UAS-Myc-fry-GFP</italic></td><td>Bloomington <break/>Drosophila <break/>Stock Center</td><td>BDSC:32106; <break/>FLYB:FBti0131207</td><td>FlyBase symbol: <break/>P{UAS-Myc-fry-GFP}2</td></tr><tr><td>Genetic reagent <break/>(<italic>D. melanogaster</italic>)</td><td><italic>UAS-Fak-GFP</italic></td><td>Gift. PMID: 15525665</td><td>FLYB:FBtp0020317</td><td>FlyBase symbol: <break/>P{UAS-Fak.EGFP}</td></tr><tr><td>Genetic reagent <break/>(<italic>D. melanogaster</italic>)</td><td><italic>UAS-muskelin-GFP</italic></td><td>Bloomington <break/>Drosophila Stock <break/>Center</td><td>BDSC:65860; <break/>FLYB:FBti0183089</td><td>FlyBase symbol: <break/>P{UASp-muskelin. <break/>GFP}attP2</td></tr><tr><td>Genetic reagent <break/>(<italic>D. melanogaster</italic>)</td><td><italic>UAS-roc2-GFP</italic></td><td>Bloomington <break/>Drosophila <break/>Stock Center</td><td>BDSC:65861; <break/>FLYB:FBti0183090</td><td>FlyBase symbol: <break/>P{UASp-Roc2.GFP}attP2</td></tr><tr><td>Genetic reagent <break/>(<italic>D. melanogaster</italic>) <break/></td><td><italic>UAS-GFP-cora1-383</italic></td><td>This paper</td><td/><td>Created by injecting <break/><italic>UAS-GFP-cora1-383</italic> DNA <break/>into flies with the <break/><italic>VK00027</italic> attP docking site</td></tr><tr><td>Strain, strain <break/>background <break/>(<italic>Danio rerio</italic>)</td><td><italic>TgBAC(tp63:GAL4FF)la213</italic></td><td>PMID: 25589751</td><td>RRID:<ext-link ext-link-type="uri" xlink:href="https://scicrunch.org/resolver/ZFIN_ZDB-ALT-150424-4">ZFIN_ZDB-ALT-150424-4</ext-link></td><td>NA</td></tr><tr><td>Strain, strain <break/>background <break/>(<italic>Danio rerio</italic>)</td><td><italic>Tg(isl1[ss]: LEXA-VP16,LEXAop:tdTomato)la215</italic></td><td>PMID: 25589751</td><td>RRID:<ext-link ext-link-type="uri" xlink:href="https://scicrunch.org/resolver/ZFIN_ZDB-ALT-150424-6">ZFIN_ZDB-ALT-150424-6</ext-link></td><td>NA</td></tr><tr><td>Strain, strain <break/>background <break/>(<italic>Danio rerio</italic>)</td><td><italic>Tg(isl1:GAL4-VP16,UAS:EGFP)zf154</italic></td><td>PMID: 15886097</td><td>RRID:<ext-link ext-link-type="uri" xlink:href="https://scicrunch.org/resolver/ZFIN_ZDB-ALT-090917-1">ZFIN_ZDB-ALT-090917-1</ext-link></td><td>NA</td></tr><tr><td>Strain, strain <break/>background <break/>(<italic>Danio rerio</italic>)</td><td><italic>Tg(isl1:GAL4-VP16</italic> <break/><break/><italic>,UAS:RFP)zf234</italic></td><td>PMID: 19962310</td><td>RRID:<ext-link ext-link-type="uri" xlink:href="https://scicrunch.org/resolver/ZFIN_ZDB-ALT-110520-2">ZFIN_ZDB-ALT-110520-2</ext-link></td><td>NA</td></tr><tr><td>Strain, strain <break/>background <break/>(<italic>Danio rerio</italic>)</td><td><italic>Tg(UAS:EGFP-PH-PLC)la216</italic></td><td>This paper</td><td>NA</td><td>Created by <break/>co-injection of <break/><italic>pDEST-4xUASnr-EGFP-PH-PLC-pA</italic> <break/>and <italic>tol2</italic> mRNA</td></tr><tr><td>Strain, strain <break/>background <break/>(<italic>Danio rerio</italic>)</td><td><italic>Tg(UAS:lifeact-GFP)mu271</italic></td><td>PMID: 23698350</td><td>RRID:<ext-link ext-link-type="uri" xlink:href="https://scicrunch.org/resolver/ZFIN_ZDB-ALT-130624-2">ZFIN_ZDB-ALT-130624-2</ext-link></td><td>NA</td></tr><tr><td>Strain, strain <break/>background <break/>(<italic>Danio rerio</italic>)</td><td><italic>Tg(UAS:GFP-CAAX)pd1025</italic></td><td>PMID: 23460678</td><td>RRID:<ext-link ext-link-type="uri" xlink:href="https://scicrunch.org/resolver/ZFIN_ZDB-ALT-130409-2">ZFIN_ZDB-ALT-130409-2</ext-link></td><td>NA</td></tr><tr><td>Strain, strain background <break/>(<italic>Danio rerio</italic>)</td><td><italic>Gt(jupa-citrine)ct520a</italic></td><td>PMID: 22056673</td><td>RRID:<ext-link ext-link-type="uri" xlink:href="https://scicrunch.org/resolver/ZFIN_ZDB-ALT-170123-1">ZFIN_ZDB-</ext-link> <break/><ext-link ext-link-type="uri" xlink:href="https://scicrunch.org/resolver/ZFIN_ZDB-ALT-170123-1">ALT-170123-1</ext-link></td><td>NA</td></tr><tr><td>Strain, strain <break/>background <break/>(<italic>Danio rerio</italic>)</td><td><italic>Gt(ctnna-citrine)ct3a</italic></td><td>PMID: 22056673</td><td>RRID:<ext-link ext-link-type="uri" xlink:href="https://scicrunch.org/resolver/ZFIN_ZDB-ALT-111010-23">ZFIN_ZDB-ALT-111010-23</ext-link></td><td>NA</td></tr><tr><td>Strain, strain <break/>background <break/>(<italic>Danio rerio</italic>)</td><td><italic>Gt(cdh1-tdtomato)xt18</italic></td><td>PMID: 30504889</td><td>NA</td><td>NA</td></tr><tr><td>Strain, strain <break/>background <break/>(<italic>Danio rerio</italic>)</td><td><italic>AB (Wild-Type)</italic></td><td>Other</td><td>NA</td><td>Sagasti Lab stock</td></tr><tr><td>Antibody</td><td>Rabbit polyclonal <break/>anti-GFP antibody</td><td>Thermo Fisher <break/>Scientific</td><td>Thermo Fisher <break/>Scientific: A-11122; <break/>RRID:<ext-link ext-link-type="uri" xlink:href="https://scicrunch.org/resolver/AB_221569">AB_221569</ext-link></td><td>1:500; overnight at 4&#176;C</td></tr><tr><td>Antibody</td><td>Mouse anti-GFP <break/>monoclonal antibody <break/>clone 3E6</td><td>Thermo Fisher <break/>Scientific</td><td>Thermo Fisher <break/>Scientific: A-11120; <break/>RRID:<ext-link ext-link-type="uri" xlink:href="https://scicrunch.org/resolver/AB_221568">AB_221568</ext-link></td><td>1:500; overnight at 4&#176;C</td></tr><tr><td>Antibody</td><td>Rabbit polyclonal <break/>anti-dsRed antibody</td><td>Clontech</td><td>Clontech Cat# 632496; <break/>RRID:<ext-link ext-link-type="uri" xlink:href="https://scicrunch.org/resolver/AB_10013483">AB_10013483</ext-link></td><td>1:500; overnight at 4&#176;C</td></tr><tr><td>Antibody</td><td>Mouse anti-coracle <break/>monoclonal antibody</td><td>Developmental <break/>Studies Hybridoma <break/>Bank</td><td>DSHB Cat# <break/>c566.9; <break/>RRID:<ext-link ext-link-type="uri" xlink:href="https://scicrunch.org/resolver/AB_1161642">AB_1161642</ext-link></td><td>1:25; overnight at 4&#176;C</td></tr><tr><td>Antibody</td><td>Goat anti-mouse <break/>IgG (H&#160;+&#160;L) <break/>cross-adsorbed <break/>secondary antibody, <break/>Alexa Fluor 568</td><td>Thermo Fisher <break/>Scientific</td><td>Thermo Fisher <break/>Scientific: A-11004; <break/>RRID:<ext-link ext-link-type="uri" xlink:href="https://scicrunch.org/resolver/AB_2534072">AB_2534072</ext-link></td><td>1:500; 2 h at 23&#176;C</td></tr><tr><td>Antibody</td><td>Goat anti-rabbit <break/>IgG (H&#160;+&#160;L) <break/>cross-adsorbed <break/>secondary antibody, <break/>Alexa Fluor 555</td><td>Thermo Fisher <break/>Scientific</td><td>Thermo Fisher <break/>Scientific: A-21428; <break/>RRID:<ext-link ext-link-type="uri" xlink:href="https://scicrunch.org/resolver/AB_2535849">AB_2535849</ext-link></td><td>1:100; 4 h at 23&#176;C</td></tr><tr><td>Antibody</td><td>Goat anti-mouse <break/>IgG (H&#160;+&#160;L) <break/>cross-adsorbed <break/>secondary antibody, <break/>Alexa Fluor 488</td><td>Thermo Fisher <break/>Scientific</td><td>Thermo Fisher <break/>Scientific: A-31561; <break/>RRID:<ext-link ext-link-type="uri" xlink:href="https://scicrunch.org/resolver/AB_2536175">AB_2536175</ext-link></td><td>1:100; 4 h at 23&#176;C</td></tr><tr><td>Antibody</td><td>Goat anti-rabbit <break/>IgG (H&#160;+&#160;L) <break/>cross-adsorbed <break/>secondary antibody, <break/>Alexa Fluor 488</td><td>Thermo Fisher <break/>Scientific</td><td>Thermo Fisher <break/>Scientific: A-11034; <break/>RRID:<ext-link ext-link-type="uri" xlink:href="https://scicrunch.org/resolver/AB_2576217">AB_2576217</ext-link></td><td>1:100; 4 h at 23&#176;C</td></tr><tr><td>Antibody</td><td>Donkey anti-rabbit <break/>IgG (H&#160;+&#160;L), ATTO <break/>565-conjugated</td><td>This study</td><td>NA</td><td>1:10; 4 h at 23&#176;C</td></tr><tr><td>Antibody</td><td>Goat anti-horseradish <break/>peroxidase IgG, <break/>affinity purified <break/>Cy5 conjugate</td><td>Jackson <break/>Immunoresearch</td><td>Jackson <break/>Immunoresearch: <break/>123-175-021</td><td/></tr><tr><td>Recombinant <break/>DNA reagent</td><td><italic>pJFRC7</italic></td><td>Addgene; <break/>PMID: 20697123</td><td>Addgene: 26220</td><td/></tr><tr><td>Recombinant <break/>DNA reagent</td><td><italic>pJFRC-MUH</italic></td><td>Addgene; <break/>PMID: 20697123</td><td>Addgene: 26213</td><td/></tr><tr><td>Recombinant <break/>DNA reagent</td><td><italic>pUAST-EndoA-GFP</italic></td><td>This paper</td><td/><td>Assembled using <break/>restriction enzyme <break/>digest</td></tr><tr><td>Recombinant <break/>DNA reagent</td><td><italic>pUAST-EndoB-GFP</italic></td><td>This paper</td><td/><td>Assembled using <break/>restriction enzyme <break/>digest</td></tr><tr><td>Recombinant <break/>DNA reagent</td><td><italic>pJFRC-MUH-</italic> <break/><italic>GFP-cora1-383</italic></td><td>This paper</td><td/><td>Assembled using <break/>restriction enzyme <break/>digest</td></tr><tr><td>Recombinant <break/>DNA reagent</td><td><italic>pAA173</italic></td><td>PMID: 18190904</td><td>NA</td><td>NA</td></tr><tr><td>Recombinant <break/>DNA reagent</td><td><italic>p5E-krtt1c19e</italic></td><td>PMID: 25589751</td><td>NA</td><td>NA</td></tr><tr><td>Recombinant <break/>DNA reagent</td><td><italic>p5E-4xUASnr</italic></td><td>PMID: 21223961</td><td>NA</td><td>NA</td></tr><tr><td>Recombinant <break/>DNA reagent</td><td><italic>pME-EGFP</italic></td><td>PMID: 17937395</td><td>NA</td><td>NA</td></tr><tr><td>Recombinant <break/>DNA reagent</td><td><italic>pME-EGFP-CAAX</italic></td><td>PMID: 17937395</td><td>NA</td><td>NA</td></tr><tr><td>Recombinant <break/>DNA reagent</td><td><italic>pME-EGFP-PH-PLC</italic></td><td>This paper</td><td>NA</td><td>Assembled using <break/>restriction enzyme <break/>digest</td></tr><tr><td>Recombinant <break/>DNA reagent</td><td><italic>p3E-pA</italic></td><td>PMID: 17937395</td><td>NA</td><td>NA</td></tr><tr><td>Recombinant <break/>DNA reagent</td><td><italic>pDEST-4xUASnr-</italic> <break/><italic>EGFP-PH-PLC-pA</italic></td><td>This paper</td><td>NA</td><td>Assembled using <break/>multisite gateway <break/>cloning</td></tr><tr><td>Recombinant <break/>DNA reagent</td><td><italic>pDEST-krtt1c19e</italic> <break/><italic>-EGFP-CAAX-pA</italic></td><td>This paper</td><td>NA</td><td>Assembled using <break/>multisite gateway <break/>cloning</td></tr><tr><td>Recombinant <break/>DNA reagent</td><td><italic>pDEST-neurod</italic> <break/><italic>5 kb:mTangerine</italic></td><td>Other</td><td>NA</td><td>Gift from Alex <break/>Nechiporuk</td></tr><tr><td>Recombinant <break/>DNA reagent</td><td><italic>pGFP-FRT-Kan-FRT</italic></td><td>PMID: 22134125</td><td>NA</td><td>NA</td></tr><tr><td>Recombinant <break/>DNA reagent</td><td>CH73-316A13</td><td>BACPAC <break/>Resources Center</td><td>NA</td><td>NA</td></tr><tr><td>Recombinant <break/>DNA reagent</td><td>CH211-120J4</td><td>BACPAC <break/>Resources Center</td><td>NA</td><td>NA</td></tr><tr><td>Recombinant <break/>DNA reagent</td><td><italic>dscl2-gfp</italic> BAC</td><td>This paper</td><td>NA</td><td>Assembled using <break/>BAC recombineering</td></tr><tr><td>Recombinant <break/>DNA reagent</td><td><italic>dspa-gfp</italic> BAC</td><td>This paper</td><td>NA</td><td>Assembled using <break/>BAC recombineering</td></tr><tr><td>Sequence-based <break/>reagent</td><td>Control morpholino</td><td>GeneTools</td><td>NA</td><td>NA</td></tr><tr><td>Sequence-based <break/>reagent</td><td><italic>neurog1</italic> <break/>morpholino</td><td>GeneTools. <break/>PMID: 12413897, <break/>12015292</td><td>NA</td><td>NA</td></tr><tr><td>Chemical <break/>compound, drug</td><td>PBP10</td><td>Sigma</td><td>Sigma Cat# 529625</td><td/></tr><tr><td>Chemical <break/>compound, drug</td><td>AG1478</td><td>Calbiochem</td><td>Calbiochem <break/>Cat#:658552</td><td>NA</td></tr><tr><td>Software, algorithm</td><td>FIMTrack</td><td>PMID: 28493862</td><td/><td><ext-link ext-link-type="uri" xlink:href="https://www.uni-muenster.de/PRIA/en/FIM/">https://www.uni-</ext-link> <break/><ext-link ext-link-type="uri" xlink:href="https://www.uni-muenster.de/PRIA/en/FIM/">muenster.de/PRIA/en/FIM/</ext-link></td></tr><tr><td>Software, algorithm</td><td>Ctrax</td><td>PMID: 19412169</td><td/><td><ext-link ext-link-type="uri" xlink:href="http://ctrax.sourceforge.net/">http://ctrax.sourceforge.net/</ext-link></td></tr><tr><td>Software, algorithm</td><td>FIJI</td><td>PMID: 22743772</td><td>Fiji, RRID:<ext-link ext-link-type="uri" xlink:href="https://scicrunch.org/resolver/SCR_002285">SCR_002285</ext-link></td><td><ext-link ext-link-type="uri" xlink:href="https://fiji.sc/">https://fiji.sc/</ext-link></td></tr><tr><td>Software, algorithm</td><td>R</td><td>R Project for <break/>Statistical <break/>Computing</td><td>R Project for <break/>Statistical Computing, <break/>RRID:<ext-link ext-link-type="uri" xlink:href="https://scicrunch.org/resolver/SCR_001905">SCR_001905</ext-link></td><td><ext-link ext-link-type="uri" xlink:href="https://www.R-project.org">https://www.R-project.org</ext-link></td></tr></tbody></table></table-wrap>