<table-wrap xmlns:xlink="http://www.w3.org/1999/xlink" id="tbl3" position="float"><object-id pub-id-type="doi">10.7554/eLife.21964.021</object-id><label>Table 3.</label><caption><p>Related to <xref ref-type="fig" rid="fig6s1">Figure 6&#8722;figure supplement 1</xref>. Correlation coefficients for pairwise combinations of factor KD. <italic>Tip60</italic> KD (a histone acetyltransferase with repressive functions in ES cells) and <italic>Brg1</italic> KD (an ATP-dependent chromatin remodeling enzyme) are included for comparison.</p><p><bold>DOI:</bold> <ext-link ext-link-type="doi" xlink:href="10.7554/eLife.21964.021">http://dx.doi.org/10.7554/eLife.21964.021</ext-link></p></caption><table frame="hsides" rules="groups"><thead><tr><th valign="top"><p><italic>Dnmt1</italic></p> </th><th valign="top"><p><italic>Tet1</italic></p> </th><th valign="top"><p><italic>Mbd3</italic></p> </th><th valign="top"><p><italic>Mbd2</italic></p> </th><th valign="top"><p><italic>Chd4</italic></p> </th><th valign="top"><p><italic>Tip60</italic></p> </th><th valign="top"><p><italic>Brg1</italic></p> </th><th valign="top"><p>KD:</p></th></tr></thead><tbody><tr><td valign="top"><p>1.0</p></td><td valign="top"><p>0.508</p></td><td valign="top"><p>0.693</p></td><td valign="top"><p>0.612</p></td><td valign="top"><p>0.645</p></td><td valign="top"><p>-0.033</p> </td><td valign="top"><p>0.051</p></td><td valign="top"><p><italic>Dnmt1</italic></p> </td></tr><tr><td valign="top"/><td valign="top"><p>1.0</p></td><td valign="top"><p>0.441</p></td><td valign="top"><p>0.551</p></td><td valign="top"><p>0.475</p></td><td valign="top"><p>-0.003</p> </td><td valign="top"><p>0.104</p></td><td valign="top"><p><italic>Tet1</italic></p> </td></tr><tr><td valign="top"/><td valign="top"/><td valign="top"><p>1.0</p></td><td valign="top"><p>0.712</p></td><td valign="top"><p>0.831</p></td><td valign="top"><p>-0.101</p> </td><td valign="top"><p>0.308</p></td><td valign="top"><p><italic>Mbd3</italic></p> </td></tr><tr><td valign="top"/><td valign="top"/><td valign="top"/><td valign="top"><p>1.0</p></td><td valign="top"><p>0.656</p></td><td valign="top"><p>-0.027</p> </td><td valign="top"><p>0.033</p></td><td valign="top"><p><italic>Mbd2</italic></p> </td></tr><tr><td valign="top"/><td valign="top"/><td valign="top"/><td valign="top"/><td valign="top"><p>1.0</p></td><td valign="top"><p>-0.094</p> </td><td valign="top"><p>0.269</p></td><td valign="top"><p><italic>Chd4</italic></p> </td></tr><tr><td valign="top"/><td valign="top"/><td valign="top"/><td valign="top"/><td valign="top"/><td valign="top"><p>1.0</p></td><td valign="top"><p>0.199</p></td><td valign="top"><p><italic>Tip60</italic></p> </td></tr><tr><td valign="top"/><td valign="top"/><td valign="top"/><td valign="top"/><td valign="top"/><td valign="top"/><td valign="top"><p>1.0</p></td><td valign="top"><p><italic>Brg1</italic></p> </td></tr></tbody></table></table-wrap>